.dockerignore
.gitignore
.travis.yml
LICENSE
MANIFEST.in
README.md
derrick.spec
requirements.txt
setup.cfg
setup.py
derrick/__init__.py
derrick/derrick.py
derrick/commands/__init__.py
derrick/commands/config.py
derrick/commands/init.py
derrick/commands/up.py
derrick/core/__init__.py
derrick/core/cache.py
derrick/core/command.py
derrick/core/command_manager.py
derrick/core/common.py
derrick/core/derrick.py
derrick/core/detector.py
derrick/core/detector_report.py
derrick/core/engine.py
derrick/core/engine_manager.py
derrick/core/exceptions.py
derrick/core/extension.py
derrick/core/logger.py
derrick/core/models.py
derrick/core/module_loader.py
derrick/core/recorder.py
derrick/core/rigging.py
derrick/core/rigging_manager.py
derrick/detectors/__init__.py
derrick/detectors/general/__init__.py
derrick/detectors/general/derrick.py
derrick/detectors/general/image_repo.py
derrick/detectors/image/__init__.py
derrick/detectors/image/golang.py
derrick/detectors/image/java.py
derrick/detectors/image/node.py
derrick/detectors/image/php.py
derrick/detectors/image/python.py
derrick/detectors/platform/__init__.py
derrick/detectors/platform/golang/__init__.py
derrick/detectors/platform/golang/package_name.py
derrick/detectors/platform/python/__init__.py
derrick/detectors/platform/python/framework.py
derrick/detectors/platform/python/package_manager.py
derrick/engines/__init__.py
derrick/engines/kubernetes_engine.py
derrick/engines/swarm_engine.py
derrick/rigging/__init__.py
derrick/rigging/golang_rigging/__init__.py
derrick/rigging/golang_rigging/golang_rigging.py
derrick/rigging/golang_rigging/templates/.dockerignore
derrick/rigging/golang_rigging/templates/Dockerfile.j2
derrick/rigging/golang_rigging/templates/Jenkinsfile.j2
derrick/rigging/golang_rigging/templates/docker-compose.yml.j2
derrick/rigging/golang_rigging/templates/kubernetes-deployment.yaml.j2
derrick/rigging/maven_rigging/__init__.py
derrick/rigging/maven_rigging/maven_rigging.py
python_derrick.egg-info/PKG-INFO
python_derrick.egg-info/SOURCES.txt
python_derrick.egg-info/dependency_links.txt
python_derrick.egg-info/entry_points.txt
python_derrick.egg-info/requires.txt
python_derrick.egg-info/top_level.txt
