Metadata-Version: 1.0
Name: python-derrick
Version: 0.1.1
Summary: An automation tool to help you dockerize App in seconds
Home-page: https://github.com/alibaba/derrick
Author: ringtail
Author-email: zhongwei.lzw@alibaba-inc.com
License: UNKNOWN
Keywords: Docker dockerize automation dockerfile docker-compose Jenkinsfile DevOps
Platform: UNKNOWN
